.gitignore
LICENSE
MANIFEST.in
README.md
setup.py
ssh_ca_example.conf
scripts/get_cert
scripts/sign_host_key
scripts/sign_key
ssh_ca/__init__.py
ssh_ca/agent_client.py
ssh_ca/s3.py
ssh_ca/utils.py
ssh_ca.egg-info/PKG-INFO
ssh_ca.egg-info/SOURCES.txt
ssh_ca.egg-info/dependency_links.txt
ssh_ca.egg-info/top_level.txt