Metadata-Version: 1.0
Name: ssh-ca
Version: 0.3.2
Summary: SSH CA utilities
Home-page: https://github.com/cloudtools/ssh-ca
Author: Mark Peek
Author-email: mark@peek.org
License: New BSD license
Platform: UNKNOWN
